{
  "slug": "falls-creek-hotham-crossing",
  "name": "Falls Creek to Hotham Crossing",
  "country": "Australia",
  "tier": 4,
  "result": {
    "status": "FICTIONAL",
    "evidence_count": 0,
    "official_website": null,
    "results_url": null,
    "evidence_summary": "No evidence of a cross-country ski race named 'Falls Creek to Hotham Crossing' found in any search results. The route exists as a popular summer hiking trail (Falls to Hotham Alpine Crossing) and a walking/endurance event (Australian Grand Traverse), but no mentions of organized cross-country skiing events, results, news, or listings on Worldloppet/FIS/Ski Classics. Other results are ski cross races at Mt Hotham, not cross-country.",
    "sources": []
  },
  "citations": [
    "https://www.revolutionise.com.au/vailaus/events/296369",
    "https://www.parks.vic.gov.au/places-to-see/parks/alpine-national-park/things-to-do/falls-to-hotham-alpine-crossing",
    "https://www.skifalls.com.au/whats-on/events/summer-events/australian-grand-traverse",
    "https://www.mthotham.com.au/summer/things-to-do/events/events-whats-on/summer-2025-26/australian-grand-traverse",
    "https://www.mthotham.com.au/events/anx-ski-cross-races",
    "https://www.mthotham.com.au/summer/walking-hiking/hike-hotham/falls-to-hotham-alpine-crossing",
    "https://www.mthotham.com.au/summer/things-to-do/whats-on/events/australian-grand-traverse",
    "https://www.fallscreek.com.au/summer/summer-activities/"
  ],
  "checked_at": "2026-03-12T15:44:49Z"
}
