{
  "slug": "salpausselka-hiihto",
  "race_name": "Salpausselk\u00e4 Hiihto",
  "query": "Salpausselk\u00e4 Hiihto cross country ski race Lahti",
  "video_count": 8,
  "videos": [
    {
      "title": "Lahti, Finland, FIS World Cup, 100 year anniversary Lahti Ski Games",
      "channel": "Craig and Sherri",
      "upload_date": "20230817",
      "duration_string": "19:42",
      "view_count": 243,
      "like_count": 1,
      "description": "We were in Lahti, Finland, for a week (March 22-29, 2023) to watch the FIS\nWorld Cup Cross Country and Nordic Combined races\nat the 100th Anniversary of the Lahti Ski Games.\nOf course, we also did a little skiing .",
      "tags": [
        "Lahti",
        "Finland",
        "nordic ski"
      ],
      "url": "https://www.youtube.com/watch?v=ojQTr7n91AM"
    },
    {
      "title": "Salpausselk\u00e4 - Lahti Ski Games 2014",
      "channel": "Urheilu Idoli",
      "upload_date": "20140301",
      "duration_string": "1:07",
      "view_count": 187,
      "like_count": null,
      "description": "Salpaussel\u00e4n kisojen tunnelmaa ja urheiluidoleita. Kuka on sinun idolisi? www.urheiluidolit.fi",
      "tags": [
        "Salpausselk\u00e4 (Location)",
        "Urheiluidolit",
        "Lahti",
        "Lahti (City/Town/Village)",
        "Finland",
        "Ski",
        "Skiing (Sport)"
      ],
      "url": "https://www.youtube.com/watch?v=JAGYraFXvI0",
      "transcript": "okay\noh\ntwo things and one more week and\nfighting for the victory"
    },
    {
      "title": "Virtual Salpausselk\u00e4, Lahti 2017 FIS Nordic World Ski Championships venue",
      "channel": "Athene Exergaming",
      "upload_date": "20160513",
      "duration_string": "1:06",
      "view_count": 1479,
      "like_count": null,
      "description": "Virtual Lahti 2017 FIS Nordic World Ski Championships venue and routes. Created by CSE Entertainment Ltd., Finland.",
      "tags": [],
      "url": "https://www.youtube.com/watch?v=PtZHYknTzIo"
    },
    {
      "title": "M\u00e4kihyppy vs hiihto",
      "channel": "Lahti Ski Games / Salpaussel\u00e4n kisat",
      "upload_date": "20120304",
      "duration_string": "1:59",
      "view_count": 224,
      "like_count": 1,
      "description": "",
      "tags": [
        "lahti",
        "ski",
        "games",
        "2012",
        "salpausselk\u00e4",
        "salppuri",
        "ifs",
        "world",
        "cup",
        "skiing",
        "sikjump",
        "skimping",
        "jumping",
        "finland",
        "combined"
      ],
      "url": "https://www.youtube.com/watch?v=XaoBGcwkVk8"
    },
    {
      "title": "Adrian Solano from Venezuela at Lahti 2017 FIS Nordic World Ski Championships",
      "channel": "Martti Ranin",
      "upload_date": "20170225",
      "duration_string": "16",
      "view_count": 3014,
      "like_count": 11,
      "description": "Never give up, go Adrian! He is the new hero in Finland and great example of persistence and determination. Real \"Sisu\"!",
      "tags": [
        "venezuela",
        "skiing",
        "sisu",
        "nevergiveup",
        "gogogo",
        "lahti2017"
      ],
      "url": "https://www.youtube.com/watch?v=mRz6Z1wZ818"
    },
    {
      "title": "Krista P\u00e4rm\u00e4koski voittaa maailmancup kilpailun Lahti, Salpausselk\u00e4 2024. Kerttu Niskanen kolmas",
      "channel": "Urheilua ",
      "upload_date": "20240302",
      "duration_string": "41:01",
      "view_count": 19454,
      "like_count": 105,
      "description": "#mitali #voitto #krista #p\u00e4rm\u00e4koski #suomi #kultaa #kristap\u00e4rm\u00e4koski #kerttu #kolmas #winner #urheilu #hiihto #sports #sport #lahti #suomi #salpausselk\u00e4 #worldcup #maailmancup #crosscountry",
      "tags": [],
      "url": "https://www.youtube.com/watch?v=bZRDCQSzYoI"
    },
    {
      "title": "Cross country World Cup 20-21, Lahti, 4x7,5 km relay, men (Norwegian commentary)",
      "channel": "Euro Neuro",
      "upload_date": "20210124",
      "duration_string": "1:22:01",
      "view_count": 46796,
      "like_count": 173,
      "description": "From 24th January",
      "tags": [],
      "url": "https://www.youtube.com/watch?v=D73HvBHQ0Qw"
    },
    {
      "title": "Cross-Country Skiing - Men's 15km Classic | Full Replay | #Beijing2022",
      "channel": "Olympics",
      "upload_date": "20220211",
      "duration_string": "2:12:33",
      "view_count": 115315,
      "like_count": 971,
      "description": "\ud83d\udcf2 Subscribe to @olympics: http://oly.ch/Subscribe \n\n \n\n\n\n \n_____________________________________________________\n\ud83c\udde8\ud83c\uddf3 #Beijing2022 replays: https://oly.ch/B22Replays\n\ud83c\uddef\ud83c\uddf5 #Tokyo2020 replays: https://oly.ch/T20Replays \n\ud83d\uddde\ufe0f News from the Olympic world: https://oly.ch/News",
      "tags": [
        "Olympic Games",
        "Olympic Channel",
        "Olympic Medal",
        "Olympics",
        "IOC",
        "Olympic Sports",
        "Champion",
        "Sport",
        "Gold",
        "Silver",
        "Bronze",
        "Beijing2022",
        "Beijing 2022",
        "Olympic Games 2022",
        "Olympic Winter Games 2022",
        "Olympics 2022",
        "Winter Olympics 2022",
        "live",
        "livestream",
        "live stream",
        "beijing live",
        "olympics live",
        "winter games live",
        "free stream",
        "free livestream",
        "beijing 2022 free stream"
      ],
      "url": "https://www.youtube.com/watch?v=FcWdga8uT4A"
    }
  ]
}