{
  "slug": "tromso-skimaraton",
  "race_name": "Troms\u00f8 Skimaraton",
  "query": "Troms\u00f8 Skimaraton cross country ski race Troms\u00f8 area",
  "video_count": 9,
  "videos": [
    {
      "title": "Reindeer racing in Troms\u00f8",
      "channel": "Oops ! I made it ",
      "upload_date": "20191103",
      "duration_string": "43",
      "view_count": 150,
      "like_count": null,
      "description": "Reindeer racing in Troms\u00f8 10 February 2019",
      "tags": [],
      "url": "https://www.youtube.com/watch?v=HRHfsEellK0"
    },
    {
      "title": "Sprint race Men - Troms\u00f8 #SkimoWC23",
      "channel": "ISMF Skimo",
      "upload_date": "20230421",
      "duration_string": "3:32",
      "view_count": 3884,
      "like_count": 19,
      "description": "The main protagonists of the Sprint races of the past seasons, Arno Lietha and Oriol Cardona Coll, proved that they are just the best in this discipline. The two great rivals made it to the finals, and Lietha won ahead of the Spanish Sprint specialist by half of a ski.\n\nLietha had an exceptional season. He won five out of six Sprints and defended the small Globe for this discipline.\n\n\u25b6 WEBSITE: http://www.ismf-ski.org\n\u25b6 FACEBOOK: https://www.facebook.com/ismf.ski\n\u25b6 TWITTER: https://twitter.com/ISMFSkimo\n\u25b6 INSTAGRAM: https://www.instagram.com/ismf_world_cup",
      "tags": [
        "ISMF",
        "ISMF World Cup",
        "ISMF Ski Mountaineering",
        "SkiMo",
        "ISMF World Cup 2018",
        "Vertical Race",
        "Individual Race",
        "Sprint Race",
        "Ski",
        "Snow",
        "Mountain"
      ],
      "url": "https://www.youtube.com/watch?v=_jWxTXZdWkw"
    },
    {
      "title": "Troms\u00f8 Skimaraton 2020",
      "channel": "Thomas K. F\u00f8re",
      "upload_date": "20200215",
      "duration_string": "6:19",
      "view_count": 448,
      "like_count": 6,
      "description": "Troms\u00f8 Skimaraton l\u00f8rdag 15. februar 2020.",
      "tags": [
        "skimaraton",
        "skimarathon",
        "troms\u00f8"
      ],
      "url": "https://www.youtube.com/watch?v=RUG5-ZXabI4"
    },
    {
      "title": "Hurtigruten Langlaufen in Troms\u00f8 - 5M",
      "channel": "Jessica Kirsten Travels & Events",
      "upload_date": "20230102",
      "duration_string": "6:52",
      "view_count": 319,
      "like_count": 6,
      "description": "werbung - Alle Hurtigruten und HX Reisen sind zu BUCHEN bei mir\nJESSICA KIRSTEN\nReiseleiterin und Agentur \u2013 bei Hurtigruten seit 2002\nBeratung mit Expertenwissen \nhttps://www.travelsandevents.com/hurtigruten\n\nAnf\u00e4ngerkurs mit Hurtigruten, Ausflug auf dem \"Hausberg\" von Troms\u00f6. Hurtigruten Ausflug im Winter. Nachmittags geht es mit Skilehrerin auf die Loipe, als Anf\u00e4nger-Kurs.",
      "tags": [
        "hurtigruten ausflug",
        "ausfl\u00fcge Troms\u00f6",
        "skilaufen Troms\u00f6",
        "langlauf ausflug",
        "hurtigruten ausflug 5m",
        "cross country skifahren",
        "ausflug buchen hurtigruten"
      ],
      "url": "https://www.youtube.com/watch?v=FDPn43yLeqM"
    },
    {
      "title": "Troms\u00f8 Ski marathon with Martin Korsner | SkatePro.com",
      "channel": "SkatePro Wintersports",
      "upload_date": "20180305",
      "duration_string": "4:25",
      "view_count": 201,
      "like_count": null,
      "description": "Martin attended this year's ski marathon in Troms\u00f8, and he made a little vlog about his experience. He shared some tips and tell you a bit about his preparation and evaluation of the race. \n\nRemember to like and subscribe. \nGot any questions? Please comment and we will reply within a few days. \n\nFollow SkatePro on Social Media:\n\u25ba Instagram: https://instagram.com/skatepro.wintersports\n\u25ba Facebook: https://www.facebook.com/skateprodk\n\u25ba Snapchat: 'skatepro.com'",
      "tags": [],
      "url": "https://www.youtube.com/watch?v=s_fb64mMIF8"
    },
    {
      "title": "Start 120 km Lillehammer Troll Ski Marathon 2019",
      "channel": "Rolf Bakken",
      "upload_date": "20190407",
      "duration_string": "32",
      "view_count": 497,
      "like_count": 4,
      "description": "",
      "tags": [],
      "url": "https://www.youtube.com/watch?v=sUzx1f9etIU"
    },
    {
      "title": "2012-02-11 Troms\u00f8 Skimaraton 2012 - Oddgeir S\u00f8lvf\u00e6stersen",
      "channel": "Thomas K. F\u00f8re",
      "upload_date": "20120212",
      "duration_string": "7",
      "view_count": 205,
      "like_count": null,
      "description": "Oddgeir S\u00f8lvf\u00e6stersen, Northern Runners, leverer en imponerende skimaraton p\u00e5 s\u00f8rpef\u00f8re. Tiden ble 2:36:15, kun 35:07 bak vinneren Snorri Einarsson.",
      "tags": [
        "Northern Runners",
        "Troms\u00f8 Skimaraton",
        "ski marathon",
        "Tromso",
        "Oddgeir S\u00f8lvf\u00e6stersen"
      ],
      "url": "https://www.youtube.com/watch?v=a1Uha8ktp9U"
    },
    {
      "title": "Troms, Norway - Storstolpan and Gorzelvtind",
      "channel": "Alexander Apeland",
      "upload_date": "20200131",
      "duration_string": "4:59",
      "view_count": 390,
      "like_count": 7,
      "description": "Topptur til Storstolpan og Gorzelvtind.\nStorstolpan 977 moh.\nGorzelvtind 1072 moh. \n\nMusic: \nhttps://www.youtube.com/watch?v=yJg-Y5byMMw \nhttps://www.youtube.com/watch?v=K4DyBUG242c\n\n#Freeski #Skimo #randonee #Troms\u00f8 #Norway #Norr\u00f8na",
      "tags": [],
      "url": "https://www.youtube.com/watch?v=F25vrHh6ZQk",
      "transcript": "[Music]\noh sweet Jesus and leading us will ever\ntrust know I don't always would\nwe'll go through the wastelands through\nthe highways so my shadow through the\nsunrays and\nalong the way melodies we haven't played\nI don't know\ngoing around these walls planning to\ncreate a song\nI don't wanna miss Abby\nwe'll go\nto the wastelands through the highways\nzuma shadow through sun rays and\ndried out tears"
    },
    {
      "title": "Kayaking in Troms\u00f8",
      "channel": "Hurtigruten",
      "upload_date": "20141001",
      "duration_string": "1:32",
      "view_count": 5054,
      "like_count": 6,
      "description": "Experience the sea in an intense and exciting way. Together with your experienced guide, you paddle in the waters off the coast of Troms\u00f8 with the mountains forming a stunning backdrop. A great way to silently travel through these pristine waters and to get close to the marine wildlife. We use stable, double, sea kayaks and no paddling experience is needed to join this excursion. The guide will give you instructions and support you along the way.\n\nOur Original Norwegian Coastal Express voyage is your pure and unfiltered escape to the charming everyday life of the Norwegian coast. Come join us on an iconic journey: \n\nFacebook: https://www.facebook.com/Hurtigruten/  \nInstagram: https://www.instagram.com/hurtigruten/\nWebsite: https://global.hurtigruten.com/destinations/norway/",
      "tags": [
        "Norwegian cruise",
        "Norwegian cruise line",
        "Norway cruise ship",
        "Norway cruise",
        "cruise ship Norway"
      ],
      "url": "https://www.youtube.com/watch?v=9_CSE5Nnnr0"
    }
  ]
}