{
  "race": {
    "name": "Marcialonga",
    "slug": "marcialonga",
    "display_name": "Marcialonga",
    "tagline": "Seventy kilometers beneath the Dolomite spires — Italy's frozen masterpiece where alpine grandeur meets the longest Worldloppet classic.",
    "vitals": {
      "distance_km": 70,
      "distance_options": [
        "70km",
        "45km"
      ],
      "elevation_m": 1050,
      "altitude_m": 1100,
      "location": "Moena to Cavalese",
      "location_badge": "Trentino, Italy",
      "country": "Italy",
      "country_code": "IT",
      "region": "Trentino-Alto Adige",
      "date": "Last Sunday in January",
      "date_specific": "2026: January 25",
      "discipline": "classic",
      "field_size": 7000,
      "founded": 1971,
      "registration": "Lottery system; registration opens in summer",
      "prize_purse": null,
      "aid_stations": "6 feed stations with Italian pastries, warm drinks, and energy food",
      "cutoff_time": null,
      "website": "https://www.marcialonga.it",
      "lat": 46.3765,
      "lng": 11.5476,
      "field_size_estimate": 7000,
      "elevation_gain_m": 1050
    },
    "climate": {
      "primary": "Alpine valley winter",
      "description": "January race date means consistent cold. The valley location between Dolomite peaks provides some wind shelter but can trap cold air. Temperatures typically -10°C to -2°C. Snow is generally reliable at altitude but January warm spells can soften lower sections.",
      "typical_temp_c": "-10 to -2",
      "challenges": [
        "Cold start in January darkness",
        "Valley fog can reduce visibility in early kilometers",
        "Snow quality varies between shaded and sun-exposed valley sections",
        "Late January thaw risk at lower elevations"
      ]
    },
    "course": {
      "primary": "Point-to-point through the Val di Fiemme and Val di Fassa, following the Avisio River valley beneath the Dolomites. Rolling terrain with moderate climbs, passing through multiple villages. The course is predominantly valley-floor skiing with stunning mountain scenery above.",
      "format": "point-to-point",
      "surface": "Machine-groomed classic tracks through alpine valley terrain",
      "technical_rating": 3,
      "grooming": "World-class Worldloppet standard, expertly maintained valley tracks",
      "features": [
        "Dolomite panorama throughout the entire course",
        "Passes through historic Ladin-speaking villages",
        "Italian feed stations with local pastries and espresso",
        "Valley skiing along the Avisio River",
        "Finish in Cavalese — also a FIS World Cup venue"
      ]
    },
    "nordic_lab_rating": {
      "overall_score": 89,
      "tier": 1,
      "tier_label": "TIER 1",
      "discipline": "classic",
      "distance": 5,
      "elevation": 3,
      "altitude": 3,
      "field_size": 5,
      "prestige": 5,
      "international_draw": 5,
      "course_technicality": 3,
      "snow_reliability": 4,
      "grooming_quality": 5,
      "accessibility": 4,
      "community": 5,
      "scenery": 5,
      "organization": 5,
      "competitive_depth": 5,
      "score_note": "Maximum scenery score anchored by Dolomite views. The Italian hospitality and alpine setting create an atmosphere unmatched in long-distance skiing. Only snow reliability prevents a perfect score.",
      "tier_note": "Prestige 5 with score >= 75 confirms TIER 1"
    },
    "history": {
      "summary": "Founded in 1971 as a 70km classic race through the Val di Fiemme and Val di Fassa in the Italian Dolomites. It quickly grew into one of the most prestigious events on the Worldloppet circuit. The race celebrates the Ladin culture of the valleys and has become Italy's defining cross-country ski marathon. The Val di Fiemme has also hosted multiple FIS Nordic World Ski Championships.",
      "notable_facts": [
        "Val di Fiemme has hosted FIS Nordic World Ski Championships in 1991, 2003, and 2013",
        "The Ladin-speaking valleys are a unique cultural enclave within Italy",
        "Italian feed stations famously serve strudel, hot chocolate, and espresso",
        "One of the original founding members of the Worldloppet series",
        "Part of both Worldloppet and Ski Classics Grand Classic series",
        "The race name means 'Long March' in Italian"
      ]
    },
    "series_membership": [
      "worldloppet",
      "ski_classics_grand_classic"
    ],
    "youtube_data": {
      "researched_at": "2026-03-10",
      "search_query": "Marcialonga cross country ski race Moena to Cavalese",
      "videos": [
        {
          "video_id": "71I_k8CbnyY",
          "title": "Marcialonga 2019 1080p",
          "channel": "Tore Stensrud",
          "view_count": 447,
          "upload_date": "20190204",
          "duration_string": "6:59",
          "description": "Marcialonga 70Km Nordic cross country skiing",
          "tags": [
            "Marcialonga",
            "2019",
            "Cavalese",
            "Canazei",
            "Moena",
            "Jan Erik Halvorsen",
            "Inge Stenvoll",
            "Erik Stensrud",
            "Steinar Christensen",
            "Tore Stensrud",
            "Lars Klatran",
            "Joar Sveen",
            "Lars Holter",
            "Frode Myrmel",
            "Skirenn",
            "Nordic Ski",
            "Cross Country"
          ],
          "url": "https://www.youtube.com/watch?v=71I_k8CbnyY",
          "curated": true,
          "curation_reason": "Recent race footage in HD quality showing the 70km Nordic course from skier perspective.",
          "display_order": 4
        },
        {
          "video_id": "5y3wlEAFTHQ",
          "title": "Marcialonga, l'impresa dei «bisonti» sotto la neve",
          "channel": "IlT Quotidiano",
          "view_count": 738,
          "upload_date": "20260125",
          "duration_string": "3:21",
          "description": "Neve fitta, fatica estrema e imprese da ricordare: la Marcialonga 2026 entra nella leggenda. La 53ª edizione della granfondo di Fiemme e Fassa si è corsa in condizioni epiche, sotto una nevicata incessante che ha trasformato i 70 chilometri da Moena a Cavalese in una sfida quasi eroica. A domare il meteo e il percorso sono stati i norvegesi Kasper Stadaas ed Emilie Fleten, trionfatori di una giornata destinata a restare nella storia.",
          "tags": [],
          "url": "https://www.youtube.com/watch?v=5y3wlEAFTHQ",
          "curated": false
        },
        {
          "video_id": "2DOZLd8IVDA",
          "title": "Marcialonga 2023 Race report vlogg Magnus",
          "channel": "Magnus Högfeldt",
          "view_count": 20008,
          "upload_date": "20230203",
          "duration_string": "20:05",
          "description": "Race report från Marcialonga 2023. En film inifrån loppet, filmat med GoPro, ur åkarens (mitt) perspektiv - en vlogg över loppet. \nMarcialonga ingår i Ski Classics långloppscup i längdskidåkning och räknas som Italiens Vasalopp. Det går vid foten av Dolomiterna i en dalgång. Som åkare passerar man många små pitoreska byar på vägen mellan Moena (starten) och Cavalese (målet). \n\nInnehåll:\n00:00 Intro innan start\n01:07 Start till Canazei\n04:23 Canazei till Predazzo\n10:20 Predazzo till Molina\n13:30 Molina till Cascata\n15:00 Cascata till målet\n17:00 Målgång och after-ski",
          "tags": [
            "maricalonga",
            "ski classics",
            "cross country",
            "cross country skiing",
            "cross country ski",
            "xcski",
            "xc",
            "längdskidåkning",
            "race report",
            "lopprapport",
            "vlog",
            "vlogg",
            "club sportoffice",
            "längdskidor",
            "sportoffice",
            "worldloppet",
            "träning",
            "konditionsidrott"
          ],
          "url": "https://www.youtube.com/watch?v=2DOZLd8IVDA",
          "curated": true,
          "curation_reason": "Recent first-person race vlog with GoPro footage from skier's perspective covering the full 70km course from Moena to Cavalese.",
          "display_order": 1
        },
        {
          "video_id": "leBAFdzpu9c",
          "title": "47th Marcialonga (26.01.2020)",
          "channel": "Towards Snowbound Horizons",
          "view_count": 78,
          "upload_date": "20240627",
          "duration_string": "2:24",
          "description": "Marcialonga is called \"The Queen of Italian Nordic ski Granfondo\". For two consecutive years (2018-2019) it has won the prize “Best Event of the year” proposed by Visma Ski Classic.\nMarcialonga takes place in Val di Fiemme and Val di Fassa, mountain areas just under the majestic Dolomites, which make Trentino region one of the most attractive places in Europe to spend an holiday.\nMarcialonga represents a Story of sport and tradition that has survived for over 50 years involving everybody from 0 to 100 with different events…\n\nThe course offers two different lengths: the classic race of 70 km from Moena to Cavalese, or the Light version with the finish line in Predazzo after 45 km. The slope leads skiers through the villages of the valleys, discovering unique and suggestive views and the support of many spectators cheering for more than 7200 participants.",
          "tags": [
            "Marcialonga",
            "CrossCountrySkiing",
            "SkiMarathon",
            "NordicSkiing",
            "SkiRace",
            "WinterSports",
            "Skiing",
            "Marcialonga2020",
            "MarcialongaExperience",
            "MarcialongaRace",
            "Dolomites",
            "ItalianAlps",
            "ValDiFiemme",
            "ValDiFassa",
            "SkiLife",
            "SkiAdventure",
            "WinterWonderland",
            "OutdoorSports",
            "SkiSeason",
            "SkiCommunity",
            "SkiLovers",
            "SkiAddict",
            "SkiingPassion",
            "TowardsSnowboundHorizons",
            "SnowboundHorizons",
            "TowardsSnowboundHorizonsSkiing",
            "SnowboundHorizonsAdventure",
            "TowardsSnowboundHorizonsVideos",
            "SnowboundHorizonsExperience",
            "TowardsSnowboundHorizonsJourney"
          ],
          "url": "https://www.youtube.com/watch?v=leBAFdzpu9c",
          "curated": false
        },
        {
          "video_id": "pB_z8F-mUWc",
          "title": "hillrunner68@ Marcialonga 2015",
          "channel": "hillrunner68",
          "view_count": 1578,
          "upload_date": "20150203",
          "duration_string": "3:44",
          "description": "crosscountry classic in Val di Fiemme, Predazzo, Cavalese,#xc-ski.de",
          "tags": [
            "Cross-country Skiing (Sport)",
            "Predazzo (City/Town/Village)",
            "Marcialonga",
            "xc-ski.de"
          ],
          "url": "https://www.youtube.com/watch?v=pB_z8F-mUWc",
          "curated": false
        },
        {
          "video_id": "7vnHMNpEBnw",
          "title": "Marcialonga 2017",
          "channel": "Video Project",
          "view_count": 2896,
          "upload_date": "20170130",
          "duration_string": "9:01",
          "description": "(IT) La Marcialonga, conosciuta anche come Marcialonga di Fiemme e Fassa o Marcialonga skiing, è la più importante e famosa competizione granfondo di sci di fondo in Italia e si disputa sulle nevi delle Valli di Fiemme e Fassa (Trento), l'ultima domenica di gennaio.\n\nFonte: Wikipedia\n----------\n(EN) Marcialonga is a cross-country ski race which is arranged for the last Sunday in January in Trentino in Italy. It was first held in 1971 and has been a part of Worldloppet as long as Worldloppet has been around.[1] In 2007, it was run for the 34th time.\nThe run begins in Moena, where the skiers first go further up Fassa Valley and along Canazei, passing Moena on its way alongside Cavalese in the Fiemme Valley.\nMarcialonga runs in classic style, and is 70 km long, but in 2007, 2015 and 2017, it was shortened to 57 km due to snow problems. In 1975, 1989 and 1990 it was cancelled due to the total lack of snow on the track. A short race, Marcialonga light is 45 km, and goes from Moena to Predazzo.\n\nSource: Wikipedia\n----------\n(DE) Der Marcialonga oder Marcialonga di fiemme e fassa ist ein Skilanglaufmarathon und einer von sechzehn Läufen der Worldloppet-Serie. Der Marcialonga war wiederholt Bestandteil des Skilanglauf-Marathon-Cups und gehört seit 2011 zur Wettlaufserie von Ski Classics. Er findet im Fleimstal (Val di Fiemme) und im Fassatal (Val di Fassa) in den Dolomiten in Italien statt.\n\nQuelle: Wikipedia\n----------\n(NO) Marcialonga er et turrenn på ski som arrangeres hver siste søndag i januar i provinsen Trento i Italia. I 2017 ble rennet arrangert for 44. gang. Rennet inngår i FIS Worldloppet Cup og Ski Classics.\nRennet begynner i Moena, hvor løperne først går videre opp i Fassadalen og snur ved Cianacei og passerer Moena på sin vei mot målgang i Cavalese i Val di Fiemme. Jerry Ahrlin har løyperekorden fra 2011 med 2.49.10.\nMarcialonga foregår i klassisk stil og er 70 km langt, men i 2003, 2007, 2015 og 2017 måtte traseen forkortes til 57 km på grunn av snømangel. En forkortet løype Marcialonga light på 45 km går fra Moena til Predazzo.\n\nKilde: Wikipedia\n----------\n\n► Subscribe: https://www.youtube.com/channel/UCIMSr9ytm7zHKa5LOFDoxsg\n\n***\nMusic Credits\n\nRock Intro 2 of Audionautix is a song authorized by Creative Commons Attribution (https://creativecommons.org/licenses/by/4.0/)\nArtist: http://audionautix.com/\n\n\n\n▒Video Project▒ \nYoutube Channel\n\n© 2017",
          "tags": [
            "Marcialonga 2017",
            "Sci da fondo",
            "Nordic Ski",
            "Langlauf",
            "Langrenn",
            "Cavalese",
            "Stadio del fondo",
            "Tesero",
            "Marcialonga",
            "Val di Fiemme",
            "Trentino",
            "Italy",
            "Italien",
            "Val di Fassa",
            "марчалонга",
            "марафон марчелонга 2017",
            "#marcialonga #2017",
            "#marcialonga2017",
            "finish line",
            "arrivo",
            "Ziel"
          ],
          "url": "https://www.youtube.com/watch?v=7vnHMNpEBnw",
          "curated": false
        },
        {
          "video_id": "5KnArM3ILuA",
          "title": "❤️53a MARCIALONGA di Fassa & Fiemme ❤️- Moena - Trentino (in 4K)",
          "channel": "jamala travelling",
          "view_count": 3814,
          "upload_date": "20260125",
          "duration_string": "2:40",
          "description": "Impressioni del passaggio a Moena - Marcialonga 2026\n\n#dolomitisuperski #dolomites #dolomiten #italy #mountains #montagne #fassavalley #fassa #valledifassa #valdifiemme #cavalese #predazzo #moena #campitello #canazei #marcialonga2026 #allenamento #marcialonga #langlauf #trentino",
          "tags": [],
          "url": "https://www.youtube.com/watch?v=5KnArM3ILuA",
          "curated": false
        },
        {
          "video_id": "yfc8k69w8iY",
          "title": "Marcialonga 2021 Me standing in front of La Cascata (final 3 km uphill) loosing composure",
          "channel": "Worldloppet",
          "view_count": 277,
          "upload_date": "20220531",
          "duration_string": "1:52",
          "description": "After 67 km of skiing you stand in front of the final 3 km UPHILL to Cavalese... Madness? THIS IS MARCIALONGA! \n\nIn 2021 I skied my first Marcialonga and it was very tough but great. I definitely will do it again. Even tough I almost lost my composure. \n\nOne hint from my side: If you feel the need to pee during a ski marathon, just go! Nobody cares if you will finish 45 seconds later. \n\nRegistration Marcialonga: \nhttps://www.marcialonga.it/marcialonga_ski/\n\nWorldloppet Passport: \nhttps://www.worldloppet.com/prodotto/worldloppet-passport/\n\n#marcialonga #scidifondo #langrenn #crosscountryskiing #xcskiing",
          "tags": [],
          "url": "https://www.youtube.com/watch?v=yfc8k69w8iY",
          "transcript": "[Music]\nladies and gentlemen\ni have to cite\na movie\nmadness\nthis is much longer\noh my god\n[Applause]\n67 kilometers done i'm totally\ndone\nthere's not a single\nkilojoule of energy left in my body and\nnow\nthree kilometers uphill\ncascada to the finish that's\ni don't have the words for that i'm\nfighting against\nmy mentality\ni'm fighting against\ncoughing i'm fighting against\nevery single muscle in my body that is\nhurting\nand i'm fighting against my urgent need\nof\nstepping aside\nyou know what i mean\nbut no i cannot take this 45 seconds to\npee over there no because i would lose\nthis 45 seconds and\neveryone cares if i will be in the\nfinish after six hours and 10 minutes\nand 45 seconds and if i finish as\nfirst or 1200 seconds\nand this is the reason why i have to\nbe now\nfor two hours\nbut okay\nlet's focus\non this last three kilometers\nso",
          "curated": false
        },
        {
          "video_id": "smfN7TiUz6Q",
          "title": "MARCIALONGA  2025 SCI FONDO | FIEMME E FASSA | TRENTINO",
          "channel": "DiscoveryAlps",
          "view_count": 6196,
          "upload_date": "20250126",
          "duration_string": "3:34",
          "description": "La 52.a Marcialonga è degli stoici Emilie Fleten e Andreas Nygaard, più forti della pioggia\nPer Fleten la 2.a vittoria consecutiva in una gara fatta di cadute, recuperi e grande forma\nPer Nygaard il successo dopo 10 anni di tentativi conquistato con il lavoro di squadra e il guizzo finale\n15.a Michaela Patscheider, 32° Lorenzo Busin e continua la festa per quasi 7000 bisonti.\n“Marcialonga bagnata, Marcialonga fortunata” devono aver pensato in molti questa mattina alla partenza da Moena, quando ad accogliere bisonti e professionisti di Ski Classics c’era un vero tempo da lupi. Ma i migliori atleti al mondo delle lunghe distanze si sono dimostrati ancora una volta più forti di tutto, e al loro seguito migliaia di bisonti. I vincitori della 52.a edizione della Marcialonga di Fiemme e Fassa sono i norvegesi Emilie Fleten e Andreas Nygaard che conquistano la granfondo più amata al mondo nel segno della resilienza con un forcing di spessore sul Mur de la Stria (muro della strega).\n\n#marcialonga @ValdiFassaSkiWorldCup #valdifassa #valdifiemme #scifondo @SciClubMarcialonga",
          "tags": [
            "marcialonga",
            "sci fondo",
            "val di fassa",
            "val di fiemme",
            "marcialonga 2025"
          ],
          "url": "https://www.youtube.com/watch?v=smfN7TiUz6Q",
          "curated": false
        },
        {
          "video_id": "B4aeWBu-qDU",
          "title": "Marcialonga 2017 & Gita in Val di Fiemme (Trentino, Italia)",
          "channel": "chievoalto",
          "view_count": 1526,
          "upload_date": "20170130",
          "duration_string": "4:17",
          "description": "29.01.2017 Visma Ski Classics\nTra la Val di Fassa e la Val di Fiemme si svolge una delle gare più importanti dello sci da fondo.\nHo avuto la possibilità di vedere questa gara da due luoghi: lo stadio del fondo di Tesero e dal centro di Cavalese centro della Magnifica Comunità\n\nTrentino, Italy. Ski marathon \nBetween the Val di Fassa and Val di Fiemme it takes place one of the most important races for cross country skiing.\n\nTrentino, Italia. Mellom Val di Fassa og Val di Fiemme det foregår en av de viktigste løp for langrenn.\n\nTrentino, Italien. Zwischen dem Val di Fassa und Val di Fiemme, einem der wichtigsten Rennen für den Langlauf.\n\n29.01.2017 Висма Ski Classics\nМежду Валь-ди-Фасса и Валь-ди-Фьемме, это имеет место одно из самых важных гонок для катания на беговых лыжах.\nУ меня была возможность увидеть эту гонку два места: стадион Фонда в Tesero и центр Cavalese центра Magnificent сообщества",
          "tags": [
            "marcialonga",
            "Val di Fiemme",
            "Cavalese",
            "Stadio del fondo",
            "Lago di tesero",
            "Sci",
            "Cross country",
            "Langrenn",
            "Langlauf",
            "Visma ski classics",
            "Ski marathon",
            "лыжный спорт",
            "зимние виды спорта",
            "лыжные гонки",
            "кубок мира",
            "лыжный марафон",
            "марчелонга",
            "марафон марчелонга 2017",
            "Ski Marathon"
          ],
          "url": "https://www.youtube.com/watch?v=B4aeWBu-qDU",
          "curated": false
        },
        {
          "video_id": "icUb2HCJrOs",
          "title": "Swix Ski Classics Marcialonga 2013",
          "channel": "SC - The Ski Community",
          "view_count": 618,
          "upload_date": "20221115",
          "duration_string": "3:30:26",
          "description": "",
          "tags": [],
          "url": "https://www.youtube.com/watch?v=icUb2HCJrOs",
          "curated": false
        },
        {
          "video_id": "XaogWTKmzQE",
          "title": "Atomic / Nordic diaries - Marcialonga",
          "channel": "Atomic Skiing",
          "view_count": 14902,
          "upload_date": "20140130",
          "duration_string": "5:59",
          "description": "Atomic athletes Simen Østensen, Jørgen Aukland and Anders Aukland dominated this year's 70 km Marcialonga (Italy) finishing first, third and fifth. In this episode of Atomic's \"Nordic Diaries\", we give you a closer insight into what it takes to win one of the world's most prestigious XC long distance races. From hard training to perfect equipment, from camaraderie to collective effort. Click play to see how these guys think and feel before and after the race.\n\nVideo & Editing: Outdoor Live - www.outdoor-live.com\n\nMusic:\n\"Dust on this Broken Music Box\"  by So I'm an Islander\n\"Wild guide\" by Austin Leonard Jones\n\"The Temperature of the Air on the Bow of the Kaleetan\" by Chris Zabriskie",
          "tags": [
            "Atomic",
            "Atomic Nordic",
            "Marcialonga",
            "Redster",
            "Anders Aukland",
            "Joergen Aukland",
            "Simen Oestensen",
            "Winner",
            "Cross-country",
            "Redster skis",
            "Redster boots",
            "long distance",
            "Ski Classics",
            "val di fiemme",
            "moena",
            "cavalese",
            "canazei",
            "molina",
            "predazzo",
            "cross country ski"
          ],
          "url": "https://www.youtube.com/watch?v=XaogWTKmzQE",
          "transcript": "[Music]\nthe realer\nprofessional in in both skiing and\noutside also so\nuh yeah it's hard to say but but uh they\ntrain hard and and uh they train\ntogether and they are strong and they're\ngood Marcel longa was uh the first\nimportant race I won so for me this race\nis very special and um I started 10\ntimes and I got nine times on the podium\nso um yeah it's an important race and\nand the last Hill it's special is like 2\nand 1 12K upill and it suits me good but\num every year it's getting harder and\nharder and more and more people are\nspecializing and um yeah it's going to\nbe tough this year I\nthink I've been uh skiing with at since\n2004 it been has been a really good uh\ncooperation uh very very good service\nand uh in Long dist R the ski is really\nreally\nimportant our boxing team have done a\ngreat job with our skis and done a lot\nof testing different places in the\ntracks because it's a little bit\ndifferent in the start and here in the\nend here is more sunny and I see and up\nin the start it's more drier and\ncolder I mean lot of the schemes that we\nhave done this race so many times and we\nknow what it's all about it's more like\nuh getting back the confidence and trust\nthat what we have done is good enough\nand just go out there and do our best\nand hopefully\nit will will but there's many good SK so\nit's not just showing up and pick the\nfirst place it's not that easy you have\nto have the right the right day the\nright skis and and um yeah you have to\nhave a day\na river\nflows you can divide Marcel longa into\nthree parts actually it's the first 15K\nwhere go from the start of the Kamai\nit's gravel uphill all the way and then\nyou turn around and then it's just down\nthe Valley High Speed so uh the grp\ngroup together in in is the same group\nthat's down here 40K later so nothing\nhappens down the valley you just have to\nstay out trouble don't break any BS\ndon't scrash and then again you turn\nhere and then it's 5K to the finish\nand it's more upill and the last three\nCas pretty Ste\n[Applause]\nyou have to be really focused to get the\nthe feeding during the race and to drink\nenergy drink and uh yeah something\nhappens with the body when it pass two\ntwo and a half hour and that's when you\nreally see who's the best\nof we are\nwild of\nGRA with many rowy days to face you\nnever feel confident it's uh it's it's\nreally hard to to go there alone in the\nfront and you don't know how much power\nthe other guys in the chasing group have\nand\nuh I was uh when I went into the to the\nlast upill I was not sure at all that I\nhad enough time\nfrom ah the last 500 met\nare that's uh the most awesome feeling I\nthink you can have as an top athlete\nwhen you you work all the year to to to\nachieve this and that's just it's just\nfantastic feeling and uh that's almost\nthe those last 500 me those are the best\nuh minutes of the whole\nday really really happy for the team\nVictory no surpris I I knew he could uh\ndo this so it was uh really really good\nthat uh he managed to win much longer\nbecause it's one of the greatest race to\nwin",
          "curated": true,
          "curation_reason": "Professional race coverage with elite athlete insights, course breakdown, and detailed analysis of the three distinct race sections.",
          "display_order": 3
        },
        {
          "video_id": "wrRUT5TjVlw",
          "title": "Marcialonga 2016 double poling finish",
          "channel": "Maya Guseynova",
          "view_count": 16613,
          "upload_date": "20160201",
          "duration_string": "4:12",
          "description": "",
          "tags": [
            "double poling",
            "loppets",
            "ski",
            "cross country ski",
            "Marcialonga 2016"
          ],
          "url": "https://www.youtube.com/watch?v=wrRUT5TjVlw",
          "curated": false
        }
      ],
      "quotes": [
        {
          "text": "You can divide Marcialonga into three parts: the first 15K where you go from the start to Canazei, it's gradual uphill all the way, then you turn around and it's just down the valley high speed, then you turn again and it's 5K to the finish and it's more uphill with the last three K's pretty steep.",
          "source_video_id": "XaogWTKmzQE",
          "source_channel": "Atomic Skiing",
          "source_view_count": 14902,
          "category": "course_difficulty",
          "curated": true
        },
        {
          "text": "Something happens with the body when it passes two and a half hours and that's when you really see who's the best. You have to be really focused to get the feeding during the race and to drink energy drink.",
          "source_video_id": "XaogWTKmzQE",
          "source_channel": "Atomic Skiing",
          "source_view_count": 14902,
          "category": "race_atmosphere",
          "curated": true
        }
      ]
    }
  }
}
