{
  "race": {
    "name": "Ugra Ski Marathon",
    "slug": "ugra-ski-marathon",
    "display_name": "Ugra Ski Marathon",
    "tagline": "Fifty kilometers of flat freestyle racing on the frozen Gornaya River floodplain in Siberia's oil capital — a Russialoppet event that attracts Olympic and world champions.",
    "vitals": {
      "distance_km": 50,
      "distance_options": [
        "50km",
        "25km",
        "5km"
      ],
      "elevation_m": 50,
      "altitude_m": 50,
      "location": "Khanty-Mansiysk",
      "location_badge": "Siberia, Russia",
      "country": "Russia",
      "country_code": "RU",
      "region": "Western Siberia",
      "date": "Late March / early April",
      "date_specific": null,
      "discipline": "both",
      "field_size": 2000,
      "founded": 2013,
      "registration": "Online registration",
      "prize_purse": null,
      "aid_stations": "Feed stations along the course",
      "cutoff_time": null,
      "website": "https://ugraloppet.ru/en/",
      "lat": 61.0042,
      "lng": 69.0019,
      "field_size_estimate": 2000,
      "elevation_gain_m": 50
    },
    "climate": {
      "primary": "Siberian continental winter",
      "description": "Late March in Khanty-Mansiysk means deep continental cold with guaranteed snow cover. Temperatures range from -20°C to -2°C. Western Siberia's extreme continental climate provides the most reliable snow conditions of any marathon-distance race. Spring sun begins to warm but temperatures remain well below zero.",
      "typical_temp_c": "-20 to -2",
      "challenges": [
        "Extreme Siberian cold — can drop well below -20°C",
        "Flat exposed course — wind chill on open floodplain",
        "Remote Siberian location — complex international travel",
        "Geopolitical isolation since 2022 limits international participation"
      ]
    },
    "course": {
      "primary": "A flat 50km freestyle course on the Gornaya River floodplain in Khanty-Mansiysk, the oil-rich Khanty-Mansi Autonomous District. Mostly open terrain with minimal elevation change. The flat profile produces fast times and favors skating technique. The course is designed for both mass participation and elite racing.",
      "format": "loop",
      "surface": "Groomed floodplain and open terrain",
      "technical_rating": 1,
      "grooming": "High-quality grooming — Khanty-Mansiysk biathlon center infrastructure",
      "features": [
        "Flat Siberian floodplain — fast freestyle course",
        "Khanty-Mansiysk biathlon center infrastructure",
        "Has attracted Olympic and world champions",
        "Part of Russialoppet Super Cup",
        "Formerly Euroloppet race (2015-2017)",
        "Three distance options: 50km, 25km, 5km"
      ]
    },
    "nordic_lab_rating": {
      "overall_score": 49,
      "tier": 3,
      "tier_label": "TIER 3",
      "discipline": "skate",
      "distance": 3,
      "elevation": 1,
      "altitude": 1,
      "field_size": 3,
      "prestige": 2,
      "international_draw": 1,
      "course_technicality": 1,
      "snow_reliability": 5,
      "grooming_quality": 4,
      "accessibility": 1,
      "community": 3,
      "scenery": 2,
      "organization": 3,
      "competitive_depth": 4,
      "score_note": "Maximum snow reliability in Siberian continental climate. Strong competitive depth — has attracted Olympic champions. Large field for a Russian event. Geopolitical isolation since 2022 severely limits international draw and accessibility.",
      "tier_note": "Score 49 confirms TIER 3"
    },
    "history": {
      "summary": "The Ugra Ski Marathon, founded in 2013 in Khanty-Mansiysk, is a major Russian citizen ski event on the flat Gornaya River floodplain. Set in the oil-rich Khanty-Mansi Autonomous District of Western Siberia, it has attracted Olympic and world champions alongside mass participation. The event was part of the Russialoppet Super Cup and briefly held Euroloppet membership (2015-2017). Since 2022, geopolitical isolation has limited international participation.",
      "notable_facts": [
        "Founded in 2013 in Khanty-Mansiysk, Western Siberia",
        "Has attracted Olympic and world champions",
        "Part of Russialoppet Super Cup",
        "Formerly Euroloppet member (2015-2017)",
        "Flat course on the Gornaya River floodplain",
        "Khanty-Mansiysk is a major biathlon and Nordic sports center",
        "International participation limited since 2022 due to geopolitical isolation"
      ]
    },
    "series_membership": [
      "russialoppet"
    ],
    "youtube_data": {
      "researched_at": "2026-03-10",
      "search_query": "Ugra Ski Marathon cross country ski race Khanty-Mansiysk",
      "videos": [
        {
          "video_id": "rQjavc6Si-g",
          "title": "Trip to Ugra Ski Marathon",
          "channel": "Akadem SkiTour",
          "view_count": 210,
          "upload_date": "20150414",
          "duration_string": "2:02",
          "description": "Our short film about trip to Ugra Ski Marathon at Khanty-Mansiysk from Novosibirsk.",
          "tags": [
            "Ski",
            "Skiing (Sport)",
            "Marathon (Sport)",
            "Cross-country Skiing",
            "Ugra",
            "Khanty-Mansiysk (City/Town/Village)"
          ],
          "url": "https://www.youtube.com/watch?v=rQjavc6Si-g",
          "curated": false
        },
        {
          "video_id": "Yut8IVJo0r4",
          "title": "Ugra Ski Marathon 2014",
          "channel": "Marathon Skier magazine",
          "view_count": 785,
          "upload_date": "20150105",
          "duration_string": "3:06",
          "description": "",
          "tags": [
            "Ugraloppet",
            "Ugra Ski Marathon",
            "Khanty-Mansiysk (City/Town/Village)",
            "Russialoppet",
            "Hanty-Mansijsk",
            "Ха́нты-Манси́йск",
            "Marathon Skier",
            "Marathon ski",
            "Skiing (Sport)",
            "Cross-country Skiing",
            "Riitta-Liisa Roponen (Olympic Athlete)",
            "Ekaterina Rudakova",
            "Alexey Ivanov",
            "Alexandr Legkov",
            "Aleksandr Legkov",
            "Seraina Boner"
          ],
          "url": "https://www.youtube.com/watch?v=Yut8IVJo0r4",
          "transcript": "[Music]\nI'm here in Siberia in HTI monsky and\nukra Lop at 50 kilm skating race is just\nabout to getting started and this is my\nfirst time in Russia and I got to really\ntell you I'm really enjoying the Russian\nhospitality\nyou\nthis\nnow I'm done with the skiing and I think\nit's time to recover and get some good\nRussian food so uh I think it's time to\nparty all right so if you compare this\nrace to the other races you've done\nquite a many of Alit races now and\nyou're the specialist in in loped races\nof marathon skiing how different is this\nthe one in\nRussia um it was uh I was thinking it\nwas some more Hills it was pretty flat\nand just a then it was a bit hard in the\nwind and um it was not so much to see\nthat it will be a race just the day\nbefore but suddenly on the racing day\nthere were lots of people and it was all\nset up so it was good after\nall yeah I I agree but yeah\nokay now we have the Olympic winner here\nLov and also third today so how was this\nrace very flat and\nwindy you",
          "curated": true,
          "curation_reason": "Features international skier perspective with course conditions commentary and insights from Olympic winners about the race terrain.",
          "display_order": 3
        },
        {
          "video_id": "s2YBKPDl31g",
          "title": "Ustyugov beats Northug at the Ugra ski marathon-2017",
          "channel": "EAS SPORT",
          "view_count": 19766,
          "upload_date": "20170408",
          "duration_string": "39",
          "description": "Ugra Ski Marathon, 8 april 2017",
          "tags": [
            "Сергей Устюгов",
            "Петтер Нуртуг",
            "Югорский лыжный марафон",
            "Sergey Ustyugov",
            "Petter Northug",
            "Ugra ski marathon"
          ],
          "url": "https://www.youtube.com/watch?v=s2YBKPDl31g",
          "curated": false
        },
        {
          "video_id": "Xn6k9VvqRxw",
          "title": "Postcard from Siberia: Welcome to Khanty Mansiysk!",
          "channel": "Biathlonworld",
          "view_count": 10486,
          "upload_date": "20160316",
          "duration_string": "1:47",
          "description": "A sunny day in Western Siberia and thoughts about the season about to end.",
          "tags": [],
          "url": "https://www.youtube.com/watch?v=Xn6k9VvqRxw",
          "transcript": "[Music]\nnine times I was here in hunti and yeah\nI I like this this place here I have\nbeen here many times but it's it's\nalways nice to come\nhere uh nice nice tracks uh the weather\nis is very good here uh the shooting\nrange is very hot the track I love the\ntrack after the world championship it's\nuh more friendly and uh I don't know the\natmosphere is more uh nice everybody's a\nlittle bit TI and\nuh me I'm also happy that it's finished\nsoon\nso yeah I have won my world championship\ntitle here 2011 so I think I will always\nremember this but this also means a good\nparty in the end of the\nseason por thep and vka",
          "curated": false
        },
        {
          "video_id": "iiVXW2ATohw",
          "title": "UGRA SKI MARATHON 2017 // Югорский лыжный марафон 2017",
          "channel": "Тюменская арена",
          "view_count": 43608,
          "upload_date": "20170409",
          "duration_string": "25:52",
          "description": "Пятый \"Югорский лыжный марафон\" в Ханты-Мансийске стал битвой двух легендарных имен в современных лыжных гонках - Сергей Устюгов, выступавший на домашней трассе в свой 25-й День рождения, против норвежского двукратного олимпионика Петтера Нортуга! Более 1500 тысяч человек вышли на старт разных дистанций 8 апреля 2017 года на пойме реки Горная. Международный марафонный сезон FIS Worldloppet Cup 2016/2017 завершился в Ханты-Мансийске\n\n5th Ugra Ski Marathon in Khanty-Mansiysk (Russia) was a battle of two big names in modern cross-country - Sergey Ustiugov (RUS) and Petter Northug (NOR). More than 1500 people from 13 countries overcame different distances, including 50 kilometers, in heart of Northern Russia. Enjoy a very interesting final of FIS Worldloppet season 2016/2017!",
          "tags": [
            "FIS",
            "Сергей Устюгов",
            "Лыжные гонки",
            "Марафон",
            "Russialoppet",
            "ФЛГР"
          ],
          "url": "https://www.youtube.com/watch?v=iiVXW2ATohw",
          "curated": true,
          "curation_reason": "Comprehensive 2017 race coverage featuring the epic battle between Sergey Ustyugov and Petter Northug, showing course layout and race atmosphere.",
          "display_order": 1
        },
        {
          "video_id": "waAPt34NQug",
          "title": "Petter Northug will take part in the Ugra Ski Marathon-2017",
          "channel": "Андрей Каща",
          "view_count": 1662,
          "upload_date": "20170404",
          "duration_string": "9",
          "description": "",
          "tags": [
            "Northug",
            "Worldloppet",
            "UgraSki",
            "ugra ski marathon",
            "югорский марафон",
            "югорский лыжный марафон"
          ],
          "url": "https://www.youtube.com/watch?v=waAPt34NQug",
          "curated": false
        },
        {
          "video_id": "UrErOuEMhPw",
          "title": "ЮГОРСКИЙ  ЛЫЖНЫЙ  МАРАФОН  50 км. UGRA SKI MARATHON 50 km. 乌格拉滑雪马拉松50公里",
          "channel": "Beautiful Video",
          "view_count": 19117,
          "upload_date": "20190409",
          "duration_string": "13:47",
          "description": "АРХЕОПАРК -  https://youtu.be/IKyMlbZ5iwg\nШОУ С ...   -    https://youtu.be/E_SCF_bVirc\nГОНОЧНЫЙ  ТРЕК  -   https://youtu.be/JIH59WKmFX8\nДистанция 50км., 1 000 000 р., за первое место.\n \"ЮГОРСКИЙ  ЛЫЖНЫЙ  МАРАФОН\"  в Ханты-Мансийске проводится с 2013г. И является финальным  престижным  марафоном серии  FIS  Worldloppet Cup.\n    \"UGRA SKI MARATHON\" in Khanty-Mansiysk has been held since 2013. And is the final prestigious marathon series FIS Worldloppet Cup.\n     加入のチャンネルです。 よう、お願い申し上げます。\nВСЕХ ПРИВЕТСТВУЮ НА КАНАЛЕ.\nДЛЯ ВАС ПРЕДСТАВЛЕНЫ КРАСИВЫЕ ВИДЕО. \nYOU CAN SEE A BEAUTIFUL VIDEO. \nALL WELCOME TO THE CHANNEL.\nMY NAME IS VLADIMIR.\n你可以看到一个美丽的视频的生命亚历山大。\n 订阅的通道。 把喜欢的。 \n在夏天，他将建立自己的房子。 \n一个新的冒险，\n一种很多有趣的。 \nSubscribe to the channel. \nPut likes. \nIn the summer he will build his house. \nA new adventure, and a lot of interesting.\n\nПОДПИСЫВАЙТЕСЬ  НА  КАНАЛ\nСТАВЬТЕ  ЛАЙКИ\nДЕЛИТЕСЬ  РОЛИКАМИ",
          "tags": [
            "world",
            "世界",
            "普京",
            "приколы",
            "俄罗斯",
            "trend",
            "欧洲",
            "parodies",
            "美国",
            "模仿",
            "nature",
            "可笑",
            "пародии",
            "auto",
            "拳击",
            "music",
            "动物",
            "top",
            "自然",
            "island",
            "机械",
            "новости",
            "係食物呀",
            "Russia",
            "видео",
            "Smeshariki",
            "красивое",
            "chinese",
            "путин",
            "реклама",
            "АКЦИИ",
            "БАННЕРЫ",
            "БОНУСЫ",
            "ВОЗНАГРАЖДЕНИЯ",
            "ВЫПЛАТЫ",
            "ЗАДАНИЯ",
            "ИНСТРУКЦИИ",
            "РЕКЛАМЫ",
            "РАСШИРЕНИЕ",
            "ДЛЯ",
            "БРАУЗЕРА",
            "СОБЫТИЯ",
            "ВЕБИНАР",
            "ВИДЕОРЕКЛАМА",
            "КОНКУРС",
            "РОЗЫГРЫШ",
            "ТРАНСЛЯЦИЯ",
            "деньоденевода",
            "рыбалка",
            "ханты-мансийск",
            "2019",
            "Лыжи",
            "марафон",
            "гонки",
            "надым день оленевода 2019",
            "Ханты-Мансийск",
            "россия",
            "сургут",
            "тюмень",
            "биатлон",
            "югорский марафон 2019"
          ],
          "url": "https://www.youtube.com/watch?v=UrErOuEMhPw",
          "curated": true,
          "curation_reason": "Detailed 2019 race documentation showing the 50km course and highlighting the prestigious FIS Worldloppet Cup final marathon status.",
          "display_order": 2
        },
        {
          "video_id": "iYAVgiS8AlM",
          "title": "Югорский лыжный марафон | Ханты-Мансийск",
          "channel": "ЛыжникиНАХ",
          "view_count": 3331,
          "upload_date": "20160406",
          "duration_string": "2:15",
          "description": "В Ханты-Мансийске прошел 4 ежегодный югорский лыжный марафон от Ханты-Мансийского банка. В нем приняли участие русские и иностранные спортсмены, звезды мирового спорта, а так же любители лыжного спорта на дистанции от 5 до 50 км. Мы покажем как все это было. Подписывайтесь на наш канал: https://www.youtube.com/channel/UCuOe... \nЗанимайтесь спортом - будьте счастливы!",
          "tags": [
            "Лыжные гонки",
            "Югорский марафон",
            "Лыжный марафон",
            "Марафон",
            "Югорский лыжный марафон",
            "Лыжи",
            "Гонки",
            "ЛыжникиНАХ",
            "Ханты-Мансийский банк",
            "Спорт",
            "ЗОЖ",
            "Здоровье",
            "Массовый спорт",
            "Скорость",
            "Международные соревнования",
            "Соревнования",
            "Тренировки",
            "Лыжный спорт",
            "Гонки на лыжах",
            "50 км",
            "Югра",
            "Ханты-Мансийск",
            "Сургут",
            "ХМАО",
            "Сервис",
            "Любители спорта",
            "Полтиник",
            "Выносливость",
            "Весна",
            "Новое"
          ],
          "url": "https://www.youtube.com/watch?v=iYAVgiS8AlM",
          "transcript": "[Music]\nI\noh",
          "curated": false
        }
      ],
      "quotes": [
        {
          "text": "It was pretty flat and just a then it was a bit hard in the wind and um it was not so much to see that it will be a race just the day before but suddenly on the racing day there were lots of people and it was all set up so it was good after all.",
          "source_video_id": "Yut8IVJo0r4",
          "source_channel": "Marathon Skier magazine",
          "source_view_count": 785,
          "category": "course_difficulty",
          "curated": true
        },
        {
          "text": "Very flat and windy.",
          "source_video_id": "Yut8IVJo0r4",
          "source_channel": "Marathon Skier magazine",
          "source_view_count": 785,
          "category": "course_difficulty",
          "curated": true
        }
      ]
    }
  }
}
